[
  {
    "fleet_manager": [
      {
        "id": "cfc235e9-4ddd-4e98-8414-a24858a13f34",
        "created_at": "2023-08-28T21:53:07.897Z",
        "updated_at": "2023-08-28T22:33:03.989Z",
        "company_id": "main_entity_pk",
        "user_id": "user_entity_pk"
      },
      {
        "id": "e344a8be-555c-49ee-a3dd-9aec89360002",
        "created_at": "2023-08-28T15:25:22.469Z",
        "updated_at": "2023-08-28T13:05:22.315Z",
        "company_id": "main_entity_pk",
        "user_id": "user_entity_pk"
      },
      {
        "id": "74ff3a0f-73ca-49d9-924c-c3ce4776d591",
        "created_at": "2023-08-28T20:34:46.934Z",
        "updated_at": "2023-08-29T03:56:40.392Z",
        "company_id": "main_entity_pk",
        "user_id": "user_entity_pk"
      },
      {
        "id": "6bf30a55-8e02-4441-9c83-2624993537e4",
        "created_at": "2023-08-29T06:07:47.455Z",
        "updated_at": "2023-08-29T03:37:41.123Z",
        "company_id": "main_entity_pk",
        "user_id": "user_entity_pk"
      },
      {
        "id": "17193adf-b35f-4123-adcc-543616377192",
        "created_at": "2023-08-28T16:01:38.940Z",
        "updated_at": "2023-08-29T08:59:51.427Z",
        "company_id": "main_entity_pk",
        "user_id": "user_entity_pk"
      }
    ],
    "car": [
      {
        "id": "5e575ec7-8132-4965-9d90-2719555cea13",
        "make": "Toyota",
        "model": "Camry",
        "year": 30308,
        "location": "New York",
        "status": "Available",
        "created_at": "2023-08-28T13:36:35.158Z",
        "updated_at": "2023-08-29T06:00:03.253Z",
        "fleet_manager_id": "17193adf-b35f-4123-adcc-543616377192"
      },
      {
        "id": "8d8e3796-c96a-4088-9dd6-e8588628a3e4",
        "make": "Honda",
        "model": "Civic",
        "year": 66278,
        "location": "Los Angeles",
        "status": "Booked",
        "created_at": "2023-08-29T05:52:41.478Z",
        "updated_at": "2023-08-28T15:55:04.253Z",
        "fleet_manager_id": "17193adf-b35f-4123-adcc-543616377192"
      },
      {
        "id": "446de62f-f7a4-4f6b-89d9-91c9472b2cfd",
        "make": "Ford",
        "model": "Mustang",
        "year": 96092,
        "location": "Chicago",
        "status": "In Repair",
        "created_at": "2023-08-28T21:40:00.657Z",
        "updated_at": "2023-08-28T23:34:08.826Z",
        "fleet_manager_id": "6bf30a55-8e02-4441-9c83-2624993537e4"
      },
      {
        "id": "63a299df-b18e-42ef-967b-4fba1fa4f3f4",
        "make": "Chevrolet",
        "model": "Cruze",
        "year": 54042,
        "location": "Houston",
        "status": "Out of Service",
        "created_at": "2023-08-28T23:44:48.767Z",
        "updated_at": "2023-08-28T15:13:58.398Z",
        "fleet_manager_id": "17193adf-b35f-4123-adcc-543616377192"
      },
      {
        "id": "2882947a-6325-4e6f-9164-e23afc664cca",
        "make": "BMW",
        "model": "X5",
        "year": 76950,
        "location": "Miami",
        "status": "Rented",
        "created_at": "2023-08-29T03:51:34.033Z",
        "updated_at": "2023-08-28T14:25:32.119Z",
        "fleet_manager_id": "cfc235e9-4ddd-4e98-8414-a24858a13f34"
      }
    ],
    "booking": [
      {
        "id": "89d7dd7e-58e4-4f16-a19a-66ec599b2c96",
        "start_time": "2023-08-28T21:14:10.852Z",
        "end_time": "2023-08-28T15:06:37.434Z",
        "created_at": "2023-08-28T21:01:35.293Z",
        "updated_at": "2023-08-29T10:35:23.800Z",
        "billing": "Credit Card",
        "car_id": "63a299df-b18e-42ef-967b-4fba1fa4f3f4",
        "guest_id": "user_entity_pk"
      },
      {
        "id": "bac205ca-e2db-42ab-80ee-bd7b148cedfa",
        "start_time": "2023-08-29T10:50:49.958Z",
        "end_time": "2023-08-28T13:15:19.199Z",
        "created_at": "2023-08-28T23:59:19.200Z",
        "updated_at": "2023-08-28T23:20:27.322Z",
        "billing": "PayPal",
        "car_id": "63a299df-b18e-42ef-967b-4fba1fa4f3f4",
        "guest_id": "user_entity_pk"
      },
      {
        "id": "5de0fa33-4b06-4f7d-83cc-39fcb05abff6",
        "start_time": "2023-08-29T07:03:10.182Z",
        "end_time": "2023-08-29T01:05:00.274Z",
        "created_at": "2023-08-29T06:07:19.168Z",
        "updated_at": "2023-08-28T20:51:09.290Z",
        "billing": "Bank Transfer",
        "car_id": "63a299df-b18e-42ef-967b-4fba1fa4f3f4",
        "guest_id": "user_entity_pk"
      },
      {
        "id": "a195a5f3-3ad3-45ab-942e-f59a5751f68a",
        "start_time": "2023-08-28T20:33:31.900Z",
        "end_time": "2023-08-28T21:54:56.902Z",
        "created_at": "2023-08-28T14:37:44.854Z",
        "updated_at": "2023-08-29T02:05:45.704Z",
        "billing": "Cash",
        "car_id": "8d8e3796-c96a-4088-9dd6-e8588628a3e4",
        "guest_id": "user_entity_pk"
      },
      {
        "id": "8d235df9-8ce2-4f63-bf55-53acad56bb75",
        "start_time": "2023-08-29T03:02:24.171Z",
        "end_time": "2023-08-28T21:08:46.690Z",
        "created_at": "2023-08-29T06:16:54.183Z",
        "updated_at": "2023-08-29T04:13:23.509Z",
        "billing": "Debit Card",
        "car_id": "446de62f-f7a4-4f6b-89d9-91c9472b2cfd",
        "guest_id": "user_entity_pk"
      }
    ],
    "admin": [
      {
        "id": "33f923a6-8494-4f63-8a87-76942ba0caa0",
        "created_at": "2023-08-28T20:07:49.109Z",
        "updated_at": "2023-08-28T15:40:28.678Z",
        "company_id": "main_entity_pk",
        "user_id": "user_entity_pk"
      },
      {
        "id": "b9ba56c3-33d4-4e56-b2ff-7d5c9f21a76f",
        "created_at": "2023-08-28T13:42:42.813Z",
        "updated_at": "2023-08-29T04:54:05.386Z",
        "company_id": "main_entity_pk",
        "user_id": "user_entity_pk"
      },
      {
        "id": "fc9e6223-531d-4b1f-b440-affecf952529",
        "created_at": "2023-08-28T20:02:24.706Z",
        "updated_at": "2023-08-28T12:48:25.353Z",
        "company_id": "main_entity_pk",
        "user_id": "user_entity_pk"
      },
      {
        "id": "7ef05c1f-24a6-41bd-a3f2-fed5f81a065a",
        "created_at": "2023-08-29T04:59:10.474Z",
        "updated_at": "2023-08-28T12:38:22.825Z",
        "company_id": "main_entity_pk",
        "user_id": "user_entity_pk"
      },
      {
        "id": "c1738be8-bd88-4c9d-b69b-20925435018f",
        "created_at": "2023-08-29T08:20:25.205Z",
        "updated_at": "2023-08-28T23:27:31.592Z",
        "company_id": "main_entity_pk",
        "user_id": "user_entity_pk"
      }
    ],
    "roqUser": [
      {
        "reference": "c46300f5-0d81-41d8-81f6-f7248c4b91bd",
        "email": "Ulices.Cole@gmail.com",
        "firstName": "Claire",
        "lastName": "Thiel",
        "active": true,
        "avatarUrl": "https://cloudflare-ipfs.com/ipfs/Qmd3W5DuhgHirLHGVixi6V76LhCkZUz6pnFt5AJBiyvHye/avatar/835.jpg",
        "tenantId": null
      },
      {
        "reference": "15df6ed1-8770-4fc7-b5ac-c0dbba89ddd4",
        "email": "Thalia.Bayer5@hotmail.com",
        "firstName": "Anthony",
        "lastName": "Morar",
        "active": true,
        "avatarUrl": "https://avatars.githubusercontent.com/u/97514929",
        "tenantId": null
      },
      {
        "reference": "5fe729c4-fd90-4fc5-a69f-9a344b0a230c",
        "email": "Aletha12@gmail.com",
        "firstName": "Kara",
        "lastName": "Rolfson",
        "active": true,
        "avatarUrl": "https://cloudflare-ipfs.com/ipfs/Qmd3W5DuhgHirLHGVixi6V76LhCkZUz6pnFt5AJBiyvHye/avatar/742.jpg",
        "tenantId": null
      },
      {
        "reference": "ca8e5c37-512f-4d7b-9bc4-0e0193bbfa8f",
        "email": "Scottie.Auer95@hotmail.com",
        "firstName": "Bernice",
        "lastName": "Hoeger",
        "active": true,
        "avatarUrl": "https://avatars.githubusercontent.com/u/30089567",
        "tenantId": null
      },
      {
        "reference": "cd42c483-6aa4-42c6-b72b-875ad5a99715",
        "email": "Sonya38@hotmail.com",
        "firstName": "Sigurd",
        "lastName": "Hyatt",
        "active": true,
        "avatarUrl": "https://cloudflare-ipfs.com/ipfs/Qmd3W5DuhgHirLHGVixi6V76LhCkZUz6pnFt5AJBiyvHye/avatar/1171.jpg",
        "tenantId": null
      }
    ]
  },
  {
    "fleet_manager": [
      {
        "id": "da4d824c-d424-4419-a667-be5fe614fc9a",
        "created_at": "2023-08-28T20:29:41.478Z",
        "updated_at": "2023-08-28T18:20:31.491Z",
        "company_id": "main_entity_pk",
        "user_id": "user_entity_pk"
      },
      {
        "id": "f5393779-d28d-47f2-8d2f-0c9a0dd0ddd8",
        "created_at": "2023-08-28T11:10:02.743Z",
        "updated_at": "2023-08-28T12:15:13.888Z",
        "company_id": "main_entity_pk",
        "user_id": "user_entity_pk"
      },
      {
        "id": "d168284a-3100-43a5-baae-8686fe8b2e77",
        "created_at": "2023-08-28T23:40:45.072Z",
        "updated_at": "2023-08-28T19:43:24.365Z",
        "company_id": "main_entity_pk",
        "user_id": "user_entity_pk"
      },
      {
        "id": "b5ef3de6-63bc-4a0b-88c6-4c561bbb950e",
        "created_at": "2023-08-28T12:51:24.898Z",
        "updated_at": "2023-08-28T13:30:47.686Z",
        "company_id": "main_entity_pk",
        "user_id": "user_entity_pk"
      },
      {
        "id": "0a7e5895-fd67-4688-a140-b08dfacaa386",
        "created_at": "2023-08-29T05:43:25.718Z",
        "updated_at": "2023-08-28T21:29:45.388Z",
        "company_id": "main_entity_pk",
        "user_id": "user_entity_pk"
      }
    ],
    "car": [
      {
        "id": "64ffb99c-d990-4874-816e-8f90ae48b09a",
        "make": "Toyota",
        "model": "Camry",
        "year": 29906,
        "location": "New York",
        "status": "Available",
        "created_at": "2023-08-28T18:54:05.301Z",
        "updated_at": "2023-08-29T01:16:48.836Z",
        "fleet_manager_id": "b5ef3de6-63bc-4a0b-88c6-4c561bbb950e"
      },
      {
        "id": "ea25ba74-1c16-4182-b302-f3ebbbe0d85b",
        "make": "Honda",
        "model": "Civic",
        "year": 4091,
        "location": "Los Angeles",
        "status": "Booked",
        "created_at": "2023-08-28T17:47:14.239Z",
        "updated_at": "2023-08-28T19:03:06.011Z",
        "fleet_manager_id": "b5ef3de6-63bc-4a0b-88c6-4c561bbb950e"
      },
      {
        "id": "d0c2a25a-d5a2-4cca-b82c-563b10836f2d",
        "make": "Ford",
        "model": "Mustang",
        "year": 30644,
        "location": "Chicago",
        "status": "In Repair",
        "created_at": "2023-08-28T13:32:39.844Z",
        "updated_at": "2023-08-28T20:15:20.700Z",
        "fleet_manager_id": "da4d824c-d424-4419-a667-be5fe614fc9a"
      },
      {
        "id": "e49227bf-2cf0-4b97-8b6d-b1ec211767c7",
        "make": "Chevrolet",
        "model": "Silverado",
        "year": 24680,
        "location": "Houston",
        "status": "Out of Service",
        "created_at": "2023-08-29T07:39:25.309Z",
        "updated_at": "2023-08-28T22:24:23.375Z",
        "fleet_manager_id": "0a7e5895-fd67-4688-a140-b08dfacaa386"
      },
      {
        "id": "8f05e9ca-e3fb-420e-a21e-e7f833a033e6",
        "make": "BMW",
        "model": "X5",
        "year": 26496,
        "location": "Miami",
        "status": "Rented",
        "created_at": "2023-08-28T20:50:11.504Z",
        "updated_at": "2023-08-28T18:11:56.849Z",
        "fleet_manager_id": "b5ef3de6-63bc-4a0b-88c6-4c561bbb950e"
      }
    ],
    "booking": [
      {
        "id": "2c43afec-bbd3-4fe4-9550-91c79b6d5d0c",
        "start_time": "2023-08-29T00:18:12.811Z",
        "end_time": "2023-08-29T05:25:14.970Z",
        "created_at": "2023-08-29T08:27:00.979Z",
        "updated_at": "2023-08-28T21:41:11.078Z",
        "billing": "Credit Card",
        "car_id": "d0c2a25a-d5a2-4cca-b82c-563b10836f2d",
        "guest_id": "user_entity_pk"
      },
      {
        "id": "5e9cf298-d948-483b-90f8-a7c1059c8625",
        "start_time": "2023-08-29T02:35:06.153Z",
        "end_time": "2023-08-29T07:31:33.501Z",
        "created_at": "2023-08-29T01:09:20.512Z",
        "updated_at": "2023-08-29T06:34:47.281Z",
        "billing": "PayPal",
        "car_id": "8f05e9ca-e3fb-420e-a21e-e7f833a033e6",
        "guest_id": "user_entity_pk"
      },
      {
        "id": "77991514-a033-4de7-a8e5-513048fd5ae0",
        "start_time": "2023-08-29T08:26:13.512Z",
        "end_time": "2023-08-29T05:01:09.416Z",
        "created_at": "2023-08-28T18:55:20.053Z",
        "updated_at": "2023-08-28T23:08:06.237Z",
        "billing": "Cash",
        "car_id": "8f05e9ca-e3fb-420e-a21e-e7f833a033e6",
        "guest_id": "user_entity_pk"
      },
      {
        "id": "ec477a23-8297-4adb-9413-c53dd82f20cc",
        "start_time": "2023-08-29T05:21:54.075Z",
        "end_time": "2023-08-28T19:59:25.380Z",
        "created_at": "2023-08-28T14:01:15.666Z",
        "updated_at": "2023-08-29T00:39:52.157Z",
        "billing": "Bank Transfer",
        "car_id": "d0c2a25a-d5a2-4cca-b82c-563b10836f2d",
        "guest_id": "user_entity_pk"
      },
      {
        "id": "d54c812a-0567-416a-b6b8-382afc16efd2",
        "start_time": "2023-08-29T00:08:22.760Z",
        "end_time": "2023-08-29T03:19:37.451Z",
        "created_at": "2023-08-28T16:18:33.805Z",
        "updated_at": "2023-08-28T13:12:55.973Z",
        "billing": "Venmo",
        "car_id": "64ffb99c-d990-4874-816e-8f90ae48b09a",
        "guest_id": "user_entity_pk"
      }
    ],
    "admin": [
      {
        "id": "0434f1eb-12fa-45a9-a2fb-55c10896002d",
        "created_at": "2023-08-28T16:38:45.393Z",
        "updated_at": "2023-08-28T17:59:39.145Z",
        "company_id": "main_entity_pk",
        "user_id": "user_entity_pk"
      },
      {
        "id": "0617ce24-15a7-4434-800a-967f1a962704",
        "created_at": "2023-08-29T09:42:45.619Z",
        "updated_at": "2023-08-28T10:55:42.829Z",
        "company_id": "main_entity_pk",
        "user_id": "user_entity_pk"
      },
      {
        "id": "c993b493-7fbe-419a-9104-de429a719dcd",
        "created_at": "2023-08-28T17:38:48.900Z",
        "updated_at": "2023-08-29T04:59:12.671Z",
        "company_id": "main_entity_pk",
        "user_id": "user_entity_pk"
      },
      {
        "id": "fbd6f996-6184-40b0-8634-c70b716cc0e5",
        "created_at": "2023-08-28T13:45:17.891Z",
        "updated_at": "2023-08-28T12:31:16.534Z",
        "company_id": "main_entity_pk",
        "user_id": "user_entity_pk"
      },
      {
        "id": "578e585a-9bf2-471e-858d-121cd4ac0a38",
        "created_at": "2023-08-28T20:29:10.958Z",
        "updated_at": "2023-08-29T01:20:03.132Z",
        "company_id": "main_entity_pk",
        "user_id": "user_entity_pk"
      }
    ],
    "roqUser": [
      {
        "reference": "ef148f84-108a-4ce9-8d48-ebfa609cd45b",
        "email": "Brendan.Reynolds64@gmail.com",
        "firstName": "Glenda",
        "lastName": "Leuschke",
        "active": true,
        "avatarUrl": "https://avatars.githubusercontent.com/u/11480773",
        "tenantId": null
      },
      {
        "reference": "0a06b341-e913-4196-910c-da9e89e0ea0f",
        "email": "Althea_Green42@yahoo.com",
        "firstName": "Emely",
        "lastName": "Barton-Wolff",
        "active": true,
        "avatarUrl": "https://avatars.githubusercontent.com/u/85985847",
        "tenantId": null
      },
      {
        "reference": "f33fcf46-e954-41dc-b8b0-82016eaba2dc",
        "email": "Shana_Wiza@hotmail.com",
        "firstName": "Emile",
        "lastName": "Stracke",
        "active": true,
        "avatarUrl": "https://avatars.githubusercontent.com/u/23126841",
        "tenantId": null
      },
      {
        "reference": "879c55f0-2519-42a8-a757-4801e6344a18",
        "email": "Edmond_Vandervort66@gmail.com",
        "firstName": "Joaquin",
        "lastName": "Bode",
        "active": true,
        "avatarUrl": "https://cloudflare-ipfs.com/ipfs/Qmd3W5DuhgHirLHGVixi6V76LhCkZUz6pnFt5AJBiyvHye/avatar/391.jpg",
        "tenantId": null
      },
      {
        "reference": "d34c80df-5f6f-49f7-b201-627ebf5252a2",
        "email": "Miles50@yahoo.com",
        "firstName": "Lacey",
        "lastName": "Hills",
        "active": true,
        "avatarUrl": "https://cloudflare-ipfs.com/ipfs/Qmd3W5DuhgHirLHGVixi6V76LhCkZUz6pnFt5AJBiyvHye/avatar/52.jpg",
        "tenantId": null
      }
    ]
  },
  {
    "fleet_manager": [
      {
        "id": "4aa61148-3ed1-4d94-add8-2fb2304f64c5",
        "created_at": "2023-08-28T12:06:19.625Z",
        "updated_at": "2023-08-29T03:44:14.916Z",
        "company_id": "main_entity_pk",
        "user_id": "user_entity_pk"
      },
      {
        "id": "c2f84df9-f8ed-415d-b56f-35a6adae0a87",
        "created_at": "2023-08-28T17:22:20.278Z",
        "updated_at": "2023-08-29T05:45:21.472Z",
        "company_id": "main_entity_pk",
        "user_id": "user_entity_pk"
      },
      {
        "id": "3be20534-a573-4c41-bcda-6b617fca2986",
        "created_at": "2023-08-28T16:15:32.047Z",
        "updated_at": "2023-08-28T14:02:58.030Z",
        "company_id": "main_entity_pk",
        "user_id": "user_entity_pk"
      },
      {
        "id": "3c473a83-8911-4629-89ba-8992b80d07e1",
        "created_at": "2023-08-29T05:47:00.668Z",
        "updated_at": "2023-08-28T13:41:08.053Z",
        "company_id": "main_entity_pk",
        "user_id": "user_entity_pk"
      },
      {
        "id": "25cb85de-ca9a-44d9-9e19-eb789670737c",
        "created_at": "2023-08-29T09:13:37.651Z",
        "updated_at": "2023-08-28T18:50:31.973Z",
        "company_id": "main_entity_pk",
        "user_id": "user_entity_pk"
      }
    ],
    "car": [
      {
        "id": "daa35052-d38e-4382-8cc1-6aa1b9394785",
        "make": "Toyota",
        "model": "Camry",
        "year": 49976,
        "location": "New York",
        "status": "Available",
        "created_at": "2023-08-29T10:08:17.147Z",
        "updated_at": "2023-08-28T22:52:46.453Z",
        "fleet_manager_id": "4aa61148-3ed1-4d94-add8-2fb2304f64c5"
      },
      {
        "id": "bb841992-f237-4a1f-8432-7716199fb448",
        "make": "Honda",
        "model": "Civic",
        "year": 62840,
        "location": "Los Angeles",
        "status": "Booked",
        "created_at": "2023-08-28T22:52:50.009Z",
        "updated_at": "2023-08-28T14:15:24.148Z",
        "fleet_manager_id": "3c473a83-8911-4629-89ba-8992b80d07e1"
      },
      {
        "id": "e02fd583-0177-4b64-be06-2b719359c9fe",
        "make": "Ford",
        "model": "Mustang",
        "year": 60416,
        "location": "Chicago",
        "status": "In Service",
        "created_at": "2023-08-28T18:39:47.220Z",
        "updated_at": "2023-08-28T15:32:16.127Z",
        "fleet_manager_id": "25cb85de-ca9a-44d9-9e19-eb789670737c"
      },
      {
        "id": "6d793722-5149-4097-8a7e-695b6ecdb6a0",
        "make": "Chevrolet",
        "model": "Cruze",
        "year": 74295,
        "location": "Houston",
        "status": "Under Maintenance",
        "created_at": "2023-08-28T16:32:41.038Z",
        "updated_at": "2023-08-29T01:27:33.727Z",
        "fleet_manager_id": "3be20534-a573-4c41-bcda-6b617fca2986"
      },
      {
        "id": "04f94d99-aabc-4cf4-8bd4-24aaded426f5",
        "make": "BMW",
        "model": "X5",
        "year": 17404,
        "location": "Miami",
        "status": "Sold",
        "created_at": "2023-08-29T08:48:17.342Z",
        "updated_at": "2023-08-29T06:38:43.188Z",
        "fleet_manager_id": "4aa61148-3ed1-4d94-add8-2fb2304f64c5"
      }
    ],
    "booking": [
      {
        "id": "0e75645a-8ff6-4fa0-859c-87178fb9ec92",
        "start_time": "2023-08-28T15:23:00.952Z",
        "end_time": "2023-08-28T11:06:53.248Z",
        "created_at": "2023-08-28T18:24:52.002Z",
        "updated_at": "2023-08-29T05:35:42.670Z",
        "billing": "Credit Card",
        "car_id": "e02fd583-0177-4b64-be06-2b719359c9fe",
        "guest_id": "user_entity_pk"
      },
      {
        "id": "5ed7e2a3-f157-4ce1-a029-45f9b538a7b4",
        "start_time": "2023-08-29T08:23:35.411Z",
        "end_time": "2023-08-28T11:27:03.580Z",
        "created_at": "2023-08-29T04:54:51.746Z",
        "updated_at": "2023-08-29T04:55:38.205Z",
        "billing": "PayPal",
        "car_id": "e02fd583-0177-4b64-be06-2b719359c9fe",
        "guest_id": "user_entity_pk"
      },
      {
        "id": "8a6a3f22-6e3c-4ae6-8fcb-bc736e64c19f",
        "start_time": "2023-08-28T15:25:15.736Z",
        "end_time": "2023-08-28T18:07:52.917Z",
        "created_at": "2023-08-29T01:32:50.932Z",
        "updated_at": "2023-08-29T10:52:59.422Z",
        "billing": "Bank Transfer",
        "car_id": "e02fd583-0177-4b64-be06-2b719359c9fe",
        "guest_id": "user_entity_pk"
      },
      {
        "id": "d0a16854-60a2-4ea3-ba88-71f8fe3dedf5",
        "start_time": "2023-08-29T06:29:45.028Z",
        "end_time": "2023-08-29T07:41:46.755Z",
        "created_at": "2023-08-28T13:35:20.617Z",
        "updated_at": "2023-08-29T04:11:13.318Z",
        "billing": "Cash",
        "car_id": "6d793722-5149-4097-8a7e-695b6ecdb6a0",
        "guest_id": "user_entity_pk"
      },
      {
        "id": "71897613-5e09-49d4-aa63-3699f052f3d0",
        "start_time": "2023-08-28T14:57:43.694Z",
        "end_time": "2023-08-28T18:31:38.546Z",
        "created_at": "2023-08-28T14:01:14.029Z",
        "updated_at": "2023-08-28T18:01:47.292Z",
        "billing": "Invoice",
        "car_id": "daa35052-d38e-4382-8cc1-6aa1b9394785",
        "guest_id": "user_entity_pk"
      }
    ],
    "admin": [
      {
        "id": "47405cc7-1756-4a63-9770-e1b0c55c9e4f",
        "created_at": "2023-08-29T10:32:37.195Z",
        "updated_at": "2023-08-29T01:04:52.280Z",
        "company_id": "main_entity_pk",
        "user_id": "user_entity_pk"
      },
      {
        "id": "0268dec6-1f66-4a78-9529-9814907aa765",
        "created_at": "2023-08-29T03:13:04.111Z",
        "updated_at": "2023-08-28T23:30:17.366Z",
        "company_id": "main_entity_pk",
        "user_id": "user_entity_pk"
      },
      {
        "id": "3b90d1c6-4034-44d8-a827-f90623ebdbee",
        "created_at": "2023-08-28T15:49:24.150Z",
        "updated_at": "2023-08-29T01:17:40.008Z",
        "company_id": "main_entity_pk",
        "user_id": "user_entity_pk"
      },
      {
        "id": "a3d5f4a4-014f-45b2-8b7d-4578fb8ec4f5",
        "created_at": "2023-08-28T11:02:56.353Z",
        "updated_at": "2023-08-29T00:27:28.186Z",
        "company_id": "main_entity_pk",
        "user_id": "user_entity_pk"
      },
      {
        "id": "f3b91cfe-e172-4ed8-b90e-48e31100b4b4",
        "created_at": "2023-08-29T07:48:18.509Z",
        "updated_at": "2023-08-29T03:09:33.749Z",
        "company_id": "main_entity_pk",
        "user_id": "user_entity_pk"
      }
    ],
    "roqUser": [
      {
        "reference": "1aa2bd9c-39dd-4b2c-9dc7-d4e6339a46bf",
        "email": "Maynard.Stracke@hotmail.com",
        "firstName": "Cierra",
        "lastName": "Bednar",
        "active": true,
        "avatarUrl": "https://avatars.githubusercontent.com/u/97620020",
        "tenantId": null
      },
      {
        "reference": "b540f0c4-8281-4773-9c54-61a7d6f0a177",
        "email": "Kristofer46@gmail.com",
        "firstName": "Darrell",
        "lastName": "Corwin",
        "active": true,
        "avatarUrl": "https://cloudflare-ipfs.com/ipfs/Qmd3W5DuhgHirLHGVixi6V76LhCkZUz6pnFt5AJBiyvHye/avatar/288.jpg",
        "tenantId": null
      },
      {
        "reference": "b88decdf-d182-469f-841a-70ffa0d6b72f",
        "email": "Taurean35@yahoo.com",
        "firstName": "Justina",
        "lastName": "Keebler",
        "active": true,
        "avatarUrl": "https://avatars.githubusercontent.com/u/60492131",
        "tenantId": null
      },
      {
        "reference": "ded8bb62-080f-4b02-bdaa-066a749d8293",
        "email": "Darion.Miller67@gmail.com",
        "firstName": "Harley",
        "lastName": "Hamill",
        "active": true,
        "avatarUrl": "https://avatars.githubusercontent.com/u/89698584",
        "tenantId": null
      },
      {
        "reference": "d631b6fe-fa08-459d-b530-315906d10c58",
        "email": "Ali25@hotmail.com",
        "firstName": "Ewell",
        "lastName": "Frami",
        "active": true,
        "avatarUrl": "https://avatars.githubusercontent.com/u/42902235",
        "tenantId": null
      }
    ]
  },
  {
    "fleet_manager": [
      {
        "id": "e987e47d-8f1d-4e76-b9cf-0a4cf97ba9c6",
        "created_at": "2023-08-28T21:40:42.994Z",
        "updated_at": "2023-08-28T19:15:34.291Z",
        "company_id": "main_entity_pk",
        "user_id": "user_entity_pk"
      },
      {
        "id": "f15bce71-8312-4371-98d6-77628f0c20b7",
        "created_at": "2023-08-28T15:52:04.419Z",
        "updated_at": "2023-08-29T02:23:50.323Z",
        "company_id": "main_entity_pk",
        "user_id": "user_entity_pk"
      },
      {
        "id": "ca8d139e-7ac6-47d9-bd10-39e4dd5524fe",
        "created_at": "2023-08-28T15:16:29.402Z",
        "updated_at": "2023-08-28T22:15:53.192Z",
        "company_id": "main_entity_pk",
        "user_id": "user_entity_pk"
      },
      {
        "id": "e126f3f6-229f-4de7-9e4e-22cfb9840033",
        "created_at": "2023-08-28T17:24:28.701Z",
        "updated_at": "2023-08-29T10:46:30.997Z",
        "company_id": "main_entity_pk",
        "user_id": "user_entity_pk"
      },
      {
        "id": "b20d1534-477f-4a5d-8f0b-bc87ab2a6243",
        "created_at": "2023-08-29T08:24:55.690Z",
        "updated_at": "2023-08-29T08:34:35.878Z",
        "company_id": "main_entity_pk",
        "user_id": "user_entity_pk"
      }
    ],
    "car": [
      {
        "id": "54bdc682-be6e-4ec8-974d-70a27b8e1766",
        "make": "Toyota",
        "model": "Camry",
        "year": 33111,
        "location": "New York",
        "status": "Available",
        "created_at": "2023-08-29T07:45:43.157Z",
        "updated_at": "2023-08-29T07:40:56.463Z",
        "fleet_manager_id": "b20d1534-477f-4a5d-8f0b-bc87ab2a6243"
      },
      {
        "id": "d8414228-6918-455c-8e35-2f82a466a61e",
        "make": "Honda",
        "model": "Civic",
        "year": 61544,
        "location": "Los Angeles",
        "status": "Rented",
        "created_at": "2023-08-29T04:25:27.715Z",
        "updated_at": "2023-08-29T05:56:50.709Z",
        "fleet_manager_id": "f15bce71-8312-4371-98d6-77628f0c20b7"
      },
      {
        "id": "bc4c456e-74b9-4a3c-a47b-160edfcef971",
        "make": "Ford",
        "model": "Focus",
        "year": 87477,
        "location": "Chicago",
        "status": "Under Maintenance",
        "created_at": "2023-08-29T09:54:03.512Z",
        "updated_at": "2023-08-28T10:53:54.310Z",
        "fleet_manager_id": "f15bce71-8312-4371-98d6-77628f0c20b7"
      },
      {
        "id": "b7949412-d18e-49ca-a0b3-eadecb46c333",
        "make": "Chevrolet",
        "model": "Cruze",
        "year": 6296,
        "location": "Houston",
        "status": "Out of Service",
        "created_at": "2023-08-28T15:44:42.723Z",
        "updated_at": "2023-08-28T13:19:26.339Z",
        "fleet_manager_id": "f15bce71-8312-4371-98d6-77628f0c20b7"
      },
      {
        "id": "00fbb875-61e3-4958-8b37-ba4c45e59eed",
        "make": "BMW",
        "model": "X5",
        "year": 13557,
        "location": "Miami",
        "status": "Reserved",
        "created_at": "2023-08-29T09:06:56.864Z",
        "updated_at": "2023-08-28T16:16:34.145Z",
        "fleet_manager_id": "e987e47d-8f1d-4e76-b9cf-0a4cf97ba9c6"
      }
    ],
    "booking": [
      {
        "id": "090ce617-7815-4fe0-a451-fe07b4f4b370",
        "start_time": "2023-08-28T16:18:50.461Z",
        "end_time": "2023-08-29T02:18:57.620Z",
        "created_at": "2023-08-28T11:48:20.378Z",
        "updated_at": "2023-08-29T00:11:23.204Z",
        "billing": "Credit Card",
        "car_id": "54bdc682-be6e-4ec8-974d-70a27b8e1766",
        "guest_id": "user_entity_pk"
      },
      {
        "id": "4870debf-92c4-46ad-a788-179973db6c71",
        "start_time": "2023-08-28T15:32:42.448Z",
        "end_time": "2023-08-29T01:20:47.491Z",
        "created_at": "2023-08-28T20:55:42.687Z",
        "updated_at": "2023-08-28T22:20:32.737Z",
        "billing": "PayPal",
        "car_id": "d8414228-6918-455c-8e35-2f82a466a61e",
        "guest_id": "user_entity_pk"
      },
      {
        "id": "6186ed66-db91-4915-a954-2743d4c8fb30",
        "start_time": "2023-08-29T00:59:25.139Z",
        "end_time": "2023-08-28T12:47:27.206Z",
        "created_at": "2023-08-28T14:55:05.937Z",
        "updated_at": "2023-08-29T00:05:06.122Z",
        "billing": "Bank Transfer",
        "car_id": "bc4c456e-74b9-4a3c-a47b-160edfcef971",
        "guest_id": "user_entity_pk"
      },
      {
        "id": "0bd7dd14-d910-4b9f-a411-0825b1936cce",
        "start_time": "2023-08-28T17:23:58.422Z",
        "end_time": "2023-08-28T20:27:53.162Z",
        "created_at": "2023-08-28T11:34:42.842Z",
        "updated_at": "2023-08-29T10:46:47.347Z",
        "billing": "Cash",
        "car_id": "bc4c456e-74b9-4a3c-a47b-160edfcef971",
        "guest_id": "user_entity_pk"
      },
      {
        "id": "7f2971aa-c028-40c2-a81c-6b9f248b9042",
        "start_time": "2023-08-28T22:29:34.195Z",
        "end_time": "2023-08-29T05:24:34.100Z",
        "created_at": "2023-08-28T20:51:03.735Z",
        "updated_at": "2023-08-28T16:16:07.382Z",
        "billing": "Debit Card",
        "car_id": "b7949412-d18e-49ca-a0b3-eadecb46c333",
        "guest_id": "user_entity_pk"
      }
    ],
    "admin": [
      {
        "id": "a3611944-525f-42f5-a129-f8eeaa0ba225",
        "created_at": "2023-08-29T01:13:22.929Z",
        "updated_at": "2023-08-28T22:37:43.374Z",
        "company_id": "main_entity_pk",
        "user_id": "user_entity_pk"
      },
      {
        "id": "563dc231-355c-4e29-90b4-1d1c55d528e6",
        "created_at": "2023-08-28T16:10:47.761Z",
        "updated_at": "2023-08-29T10:52:02.350Z",
        "company_id": "main_entity_pk",
        "user_id": "user_entity_pk"
      },
      {
        "id": "c2ad1e97-7f1c-485a-876d-a5d52371560a",
        "created_at": "2023-08-28T16:52:51.999Z",
        "updated_at": "2023-08-28T17:38:37.158Z",
        "company_id": "main_entity_pk",
        "user_id": "user_entity_pk"
      },
      {
        "id": "fd443d2d-f1d6-45fa-8c18-215aadd1061b",
        "created_at": "2023-08-28T21:58:03.885Z",
        "updated_at": "2023-08-28T17:25:24.497Z",
        "company_id": "main_entity_pk",
        "user_id": "user_entity_pk"
      },
      {
        "id": "6cd0ce6f-d1f4-4664-8255-d435e3f5e32d",
        "created_at": "2023-08-29T09:38:41.009Z",
        "updated_at": "2023-08-28T20:45:56.307Z",
        "company_id": "main_entity_pk",
        "user_id": "user_entity_pk"
      }
    ],
    "roqUser": [
      {
        "reference": "cca63c88-1cc8-41bd-91c4-38b4f77675bd",
        "email": "Ericka.Labadie0@gmail.com",
        "firstName": "Johnnie",
        "lastName": "Brakus",
        "active": true,
        "avatarUrl": "https://avatars.githubusercontent.com/u/14284227",
        "tenantId": null
      },
      {
        "reference": "34ccd6d3-9a70-455b-9383-b4bf0461ba67",
        "email": "Frederick74@yahoo.com",
        "firstName": "Kallie",
        "lastName": "Smitham",
        "active": true,
        "avatarUrl": "https://cloudflare-ipfs.com/ipfs/Qmd3W5DuhgHirLHGVixi6V76LhCkZUz6pnFt5AJBiyvHye/avatar/173.jpg",
        "tenantId": null
      },
      {
        "reference": "ab6d2e05-f27f-4afc-b4e1-2231a88da664",
        "email": "Brennan_Effertz@yahoo.com",
        "firstName": "Andre",
        "lastName": "Cremin",
        "active": true,
        "avatarUrl": "https://cloudflare-ipfs.com/ipfs/Qmd3W5DuhgHirLHGVixi6V76LhCkZUz6pnFt5AJBiyvHye/avatar/732.jpg",
        "tenantId": null
      },
      {
        "reference": "5b714ec9-1615-4113-8686-b6a25db79401",
        "email": "King_Feil@yahoo.com",
        "firstName": "Jamel",
        "lastName": "Jenkins",
        "active": true,
        "avatarUrl": "https://avatars.githubusercontent.com/u/26762562",
        "tenantId": null
      },
      {
        "reference": "cbd336bd-c98c-4aaa-8d8b-05dcb08233c5",
        "email": "Kacie23@gmail.com",
        "firstName": "Aurelie",
        "lastName": "Balistreri",
        "active": true,
        "avatarUrl": "https://avatars.githubusercontent.com/u/64265960",
        "tenantId": null
      }
    ]
  },
  {
    "fleet_manager": [
      {
        "id": "3ad9a40f-c486-49b8-84a1-2c2ee2bb2d42",
        "created_at": "2023-08-28T22:24:51.272Z",
        "updated_at": "2023-08-28T14:20:28.144Z",
        "company_id": "main_entity_pk",
        "user_id": "user_entity_pk"
      },
      {
        "id": "864c9f70-1ab8-4f7b-bf0b-3dfaffd6b478",
        "created_at": "2023-08-29T10:41:30.237Z",
        "updated_at": "2023-08-28T15:23:53.685Z",
        "company_id": "main_entity_pk",
        "user_id": "user_entity_pk"
      },
      {
        "id": "f62d708f-2c71-4d29-880a-3ad793504393",
        "created_at": "2023-08-28T13:20:17.204Z",
        "updated_at": "2023-08-29T01:51:51.737Z",
        "company_id": "main_entity_pk",
        "user_id": "user_entity_pk"
      },
      {
        "id": "11891122-591c-4323-a277-9b5bc1b2f76f",
        "created_at": "2023-08-28T11:18:16.125Z",
        "updated_at": "2023-08-29T01:36:53.071Z",
        "company_id": "main_entity_pk",
        "user_id": "user_entity_pk"
      },
      {
        "id": "45030733-8580-454a-b975-fb40c0396e6c",
        "created_at": "2023-08-29T02:11:05.731Z",
        "updated_at": "2023-08-29T06:00:54.705Z",
        "company_id": "main_entity_pk",
        "user_id": "user_entity_pk"
      }
    ],
    "car": [
      {
        "id": "5a614348-b972-4e6b-8e78-f26d37396333",
        "make": "Toyota",
        "model": "Camry",
        "year": 28455,
        "location": "New York",
        "status": "Available",
        "created_at": "2023-08-29T08:46:24.238Z",
        "updated_at": "2023-08-29T10:25:06.592Z",
        "fleet_manager_id": "f62d708f-2c71-4d29-880a-3ad793504393"
      },
      {
        "id": "745bd754-d26d-4ba4-9a75-e6be2bf1b290",
        "make": "Honda",
        "model": "Civic",
        "year": 13729,
        "location": "Los Angeles",
        "status": "Reserved",
        "created_at": "2023-08-28T17:16:35.753Z",
        "updated_at": "2023-08-29T08:07:36.774Z",
        "fleet_manager_id": "45030733-8580-454a-b975-fb40c0396e6c"
      },
      {
        "id": "1aa104f5-292f-4da0-9921-ed303781f286",
        "make": "Ford",
        "model": "Mustang",
        "year": 21342,
        "location": "Chicago",
        "status": "Rented",
        "created_at": "2023-08-28T14:47:35.762Z",
        "updated_at": "2023-08-28T20:22:16.127Z",
        "fleet_manager_id": "45030733-8580-454a-b975-fb40c0396e6c"
      },
      {
        "id": "182dc4ef-9ab0-4218-9c3b-fc2d0b43d1b1",
        "make": "Chevrolet",
        "model": "Silverado",
        "year": 8539,
        "location": "Houston",
        "status": "Out of service",
        "created_at": "2023-08-28T12:26:52.602Z",
        "updated_at": "2023-08-28T14:02:12.909Z",
        "fleet_manager_id": "11891122-591c-4323-a277-9b5bc1b2f76f"
      },
      {
        "id": "7b8e08b9-9aa7-4d36-8caa-233e0b940082",
        "make": "BMW",
        "model": "X5",
        "year": 3938,
        "location": "Miami",
        "status": "Maintenance",
        "created_at": "2023-08-28T22:00:09.161Z",
        "updated_at": "2023-08-28T18:06:06.754Z",
        "fleet_manager_id": "f62d708f-2c71-4d29-880a-3ad793504393"
      }
    ],
    "booking": [
      {
        "id": "2e541727-1591-4f3f-bfcf-e74aeec3f060",
        "start_time": "2023-08-29T07:28:22.710Z",
        "end_time": "2023-08-29T00:41:28.542Z",
        "created_at": "2023-08-29T01:11:40.964Z",
        "updated_at": "2023-08-29T09:53:39.631Z",
        "billing": "Credit Card",
        "car_id": "182dc4ef-9ab0-4218-9c3b-fc2d0b43d1b1",
        "guest_id": "user_entity_pk"
      },
      {
        "id": "f21429a9-62ef-4a2d-a2a1-f9461aa87bdb",
        "start_time": "2023-08-28T12:56:27.311Z",
        "end_time": "2023-08-28T21:38:36.134Z",
        "created_at": "2023-08-29T08:48:25.047Z",
        "updated_at": "2023-08-29T00:23:49.752Z",
        "billing": "PayPal",
        "car_id": "1aa104f5-292f-4da0-9921-ed303781f286",
        "guest_id": "user_entity_pk"
      },
      {
        "id": "0cb32f35-7632-4556-8fb7-97215d746b47",
        "start_time": "2023-08-29T07:59:26.143Z",
        "end_time": "2023-08-29T02:17:38.421Z",
        "created_at": "2023-08-29T01:56:09.204Z",
        "updated_at": "2023-08-29T00:02:16.330Z",
        "billing": "Bank Transfer",
        "car_id": "1aa104f5-292f-4da0-9921-ed303781f286",
        "guest_id": "user_entity_pk"
      },
      {
        "id": "7184017a-bac2-48f5-bcd1-d6d75e2107e7",
        "start_time": "2023-08-29T06:17:51.283Z",
        "end_time": "2023-08-28T11:47:33.692Z",
        "created_at": "2023-08-28T19:13:29.058Z",
        "updated_at": "2023-08-28T16:56:56.018Z",
        "billing": "Cash",
        "car_id": "5a614348-b972-4e6b-8e78-f26d37396333",
        "guest_id": "user_entity_pk"
      },
      {
        "id": "87d3e9be-4d83-4fe5-af72-dccbd294ce5a",
        "start_time": "2023-08-28T22:20:13.159Z",
        "end_time": "2023-08-29T02:32:45.613Z",
        "created_at": "2023-08-28T21:27:24.710Z",
        "updated_at": "2023-08-29T02:09:00.956Z",
        "billing": "Mobile Payment",
        "car_id": "1aa104f5-292f-4da0-9921-ed303781f286",
        "guest_id": "user_entity_pk"
      }
    ],
    "admin": [
      {
        "id": "5339d84f-f074-4528-be8c-5f5af491f4e4",
        "created_at": "2023-08-28T23:58:10.789Z",
        "updated_at": "2023-08-28T13:48:35.044Z",
        "company_id": "main_entity_pk",
        "user_id": "user_entity_pk"
      },
      {
        "id": "55e6fdd1-e07c-416c-b9cd-adb0ab62b9ed",
        "created_at": "2023-08-28T12:59:47.813Z",
        "updated_at": "2023-08-28T14:55:05.238Z",
        "company_id": "main_entity_pk",
        "user_id": "user_entity_pk"
      },
      {
        "id": "d6d1cc8b-9fa4-4c53-88bc-d4569056354f",
        "created_at": "2023-08-29T06:59:22.922Z",
        "updated_at": "2023-08-28T19:17:04.130Z",
        "company_id": "main_entity_pk",
        "user_id": "user_entity_pk"
      },
      {
        "id": "811163f4-f1fd-4dc1-9dc2-9f894424f2ca",
        "created_at": "2023-08-29T01:40:11.551Z",
        "updated_at": "2023-08-28T17:15:05.074Z",
        "company_id": "main_entity_pk",
        "user_id": "user_entity_pk"
      },
      {
        "id": "dc7bd23f-5d82-4699-a339-85d7462d8c2f",
        "created_at": "2023-08-28T18:40:05.011Z",
        "updated_at": "2023-08-28T13:25:08.739Z",
        "company_id": "main_entity_pk",
        "user_id": "user_entity_pk"
      }
    ],
    "roqUser": [
      {
        "reference": "be68f130-8721-47d6-82af-2c1d614d6387",
        "email": "Francesca.Swaniawski@hotmail.com",
        "firstName": "Eddie",
        "lastName": "Jerde-Homenick",
        "active": true,
        "avatarUrl": "https://avatars.githubusercontent.com/u/97134150",
        "tenantId": null
      },
      {
        "reference": "467b6acb-d058-4a3c-8898-7d5b17c58d3f",
        "email": "Cloyd.Parisian@hotmail.com",
        "firstName": "Vella",
        "lastName": "Torphy",
        "active": true,
        "avatarUrl": "https://avatars.githubusercontent.com/u/75454043",
        "tenantId": null
      },
      {
        "reference": "b2d4dcb3-9010-4fa1-a5f9-4bc403a631f2",
        "email": "Wendy1@gmail.com",
        "firstName": "Adolph",
        "lastName": "Gibson",
        "active": true,
        "avatarUrl": "https://cloudflare-ipfs.com/ipfs/Qmd3W5DuhgHirLHGVixi6V76LhCkZUz6pnFt5AJBiyvHye/avatar/576.jpg",
        "tenantId": null
      },
      {
        "reference": "71ca1956-4e3e-4b26-8886-f58c5d3b7e71",
        "email": "Justus10@gmail.com",
        "firstName": "Leanna",
        "lastName": "West",
        "active": true,
        "avatarUrl": "https://avatars.githubusercontent.com/u/71549024",
        "tenantId": null
      },
      {
        "reference": "89414739-3873-4686-aea0-f2bf10b8d863",
        "email": "Ashley65@hotmail.com",
        "firstName": "Cortney",
        "lastName": "Sawayn",
        "active": true,
        "avatarUrl": "https://avatars.githubusercontent.com/u/53736209",
        "tenantId": null
      }
    ]
  },
  {
    "fleet_manager": [
      {
        "id": "2cece214-12d3-424e-9e9d-59d273cb3bb0",
        "created_at": "2023-08-29T00:27:09.817Z",
        "updated_at": "2023-08-28T21:56:53.559Z",
        "company_id": "main_entity_pk",
        "user_id": "user_entity_pk"
      },
      {
        "id": "18e8f1fe-3571-4d37-9876-ed1e82b1bce6",
        "created_at": "2023-08-28T12:44:43.730Z",
        "updated_at": "2023-08-29T05:02:25.016Z",
        "company_id": "main_entity_pk",
        "user_id": "user_entity_pk"
      },
      {
        "id": "378550c0-f1af-42c1-93b1-2408d6b7dfc1",
        "created_at": "2023-08-28T14:18:44.879Z",
        "updated_at": "2023-08-28T17:17:31.975Z",
        "company_id": "main_entity_pk",
        "user_id": "user_entity_pk"
      },
      {
        "id": "bb176101-b1aa-40af-892d-1f273d428c57",
        "created_at": "2023-08-28T20:33:58.327Z",
        "updated_at": "2023-08-28T15:47:11.240Z",
        "company_id": "main_entity_pk",
        "user_id": "user_entity_pk"
      },
      {
        "id": "95827797-18b4-4188-b863-9dc7ed7a17b1",
        "created_at": "2023-08-28T15:20:58.340Z",
        "updated_at": "2023-08-28T17:12:03.868Z",
        "company_id": "main_entity_pk",
        "user_id": "user_entity_pk"
      }
    ],
    "car": [
      {
        "id": "4442890d-a01d-4440-b69b-0192074fceb5",
        "make": "Toyota",
        "model": "Camry",
        "year": 76761,
        "location": "New York",
        "status": "Available",
        "created_at": "2023-08-28T22:06:32.177Z",
        "updated_at": "2023-08-28T23:50:13.660Z",
        "fleet_manager_id": "18e8f1fe-3571-4d37-9876-ed1e82b1bce6"
      },
      {
        "id": "b273a77b-9d0a-441b-984f-a85b70607d9f",
        "make": "Honda",
        "model": "Civic",
        "year": 29973,
        "location": "Los Angeles",
        "status": "Rented",
        "created_at": "2023-08-29T10:42:18.491Z",
        "updated_at": "2023-08-28T14:09:10.356Z",
        "fleet_manager_id": "95827797-18b4-4188-b863-9dc7ed7a17b1"
      },
      {
        "id": "47810541-2d65-4f51-9d42-c6776d37587e",
        "make": "Ford",
        "model": "Mustang",
        "year": 11956,
        "location": "Chicago",
        "status": "In Repair",
        "created_at": "2023-08-29T06:08:48.557Z",
        "updated_at": "2023-08-29T03:18:56.981Z",
        "fleet_manager_id": "2cece214-12d3-424e-9e9d-59d273cb3bb0"
      },
      {
        "id": "fdc9b19a-4a97-4a25-9140-c0a7d4532fa5",
        "make": "Chevrolet",
        "model": "Silverado",
        "year": 1858,
        "location": "Houston",
        "status": "Out of Service",
        "created_at": "2023-08-28T19:14:15.488Z",
        "updated_at": "2023-08-28T23:49:15.118Z",
        "fleet_manager_id": "2cece214-12d3-424e-9e9d-59d273cb3bb0"
      },
      {
        "id": "b33daf93-cf59-4eaf-97eb-3a43f3d350f5",
        "make": "BMW",
        "model": "X5",
        "year": 11180,
        "location": "Miami",
        "status": "Reserved",
        "created_at": "2023-08-29T07:40:20.437Z",
        "updated_at": "2023-08-28T13:28:27.145Z",
        "fleet_manager_id": "378550c0-f1af-42c1-93b1-2408d6b7dfc1"
      }
    ],
    "booking": [
      {
        "id": "d343bc9a-2f50-46f9-af66-d7f25e9177b8",
        "start_time": "2023-08-29T09:49:25.356Z",
        "end_time": "2023-08-28T11:24:07.948Z",
        "created_at": "2023-08-28T19:29:42.286Z",
        "updated_at": "2023-08-29T07:03:11.283Z",
        "billing": "Credit Card",
        "car_id": "47810541-2d65-4f51-9d42-c6776d37587e",
        "guest_id": "user_entity_pk"
      },
      {
        "id": "3b1adc1a-bfcc-4eef-bb59-c094332f3547",
        "start_time": "2023-08-28T20:07:04.429Z",
        "end_time": "2023-08-29T00:33:59.264Z",
        "created_at": "2023-08-29T05:27:21.086Z",
        "updated_at": "2023-08-29T00:24:52.048Z",
        "billing": "PayPal",
        "car_id": "4442890d-a01d-4440-b69b-0192074fceb5",
        "guest_id": "user_entity_pk"
      },
      {
        "id": "0e16573a-5ee5-4bdb-95d8-d256ec0144e9",
        "start_time": "2023-08-28T17:17:15.573Z",
        "end_time": "2023-08-28T20:51:18.291Z",
        "created_at": "2023-08-29T06:14:41.986Z",
        "updated_at": "2023-08-28T23:40:34.672Z",
        "billing": "Bank Transfer",
        "car_id": "47810541-2d65-4f51-9d42-c6776d37587e",
        "guest_id": "user_entity_pk"
      },
      {
        "id": "4cdc4d11-0b2e-4c0a-9e88-d2ea442064bf",
        "start_time": "2023-08-29T06:23:18.711Z",
        "end_time": "2023-08-29T03:06:33.009Z",
        "created_at": "2023-08-28T11:54:30.688Z",
        "updated_at": "2023-08-29T00:43:31.585Z",
        "billing": "Cash",
        "car_id": "b273a77b-9d0a-441b-984f-a85b70607d9f",
        "guest_id": "user_entity_pk"
      },
      {
        "id": "a5a4193c-0ad3-4379-b027-078e9ee450e1",
        "start_time": "2023-08-28T12:12:58.871Z",
        "end_time": "2023-08-28T17:35:43.407Z",
        "created_at": "2023-08-28T18:37:53.781Z",
        "updated_at": "2023-08-28T23:45:46.331Z",
        "billing": "Invoice",
        "car_id": "b33daf93-cf59-4eaf-97eb-3a43f3d350f5",
        "guest_id": "user_entity_pk"
      }
    ],
    "admin": [
      {
        "id": "34c064ec-af0a-4b73-9921-be84266ae4e7",
        "created_at": "2023-08-28T14:37:04.000Z",
        "updated_at": "2023-08-29T00:15:42.754Z",
        "company_id": "main_entity_pk",
        "user_id": "user_entity_pk"
      },
      {
        "id": "98e25e7d-d8c8-4d44-a6e1-d99be25bcbed",
        "created_at": "2023-08-29T00:10:05.246Z",
        "updated_at": "2023-08-28T12:01:56.407Z",
        "company_id": "main_entity_pk",
        "user_id": "user_entity_pk"
      },
      {
        "id": "143a7818-e44d-468e-8a24-9ac58e4c5371",
        "created_at": "2023-08-28T21:58:39.899Z",
        "updated_at": "2023-08-28T22:34:40.395Z",
        "company_id": "main_entity_pk",
        "user_id": "user_entity_pk"
      },
      {
        "id": "0a88ef89-1ab7-4db3-8ab5-aa78529e523f",
        "created_at": "2023-08-28T23:36:19.480Z",
        "updated_at": "2023-08-29T09:39:22.015Z",
        "company_id": "main_entity_pk",
        "user_id": "user_entity_pk"
      },
      {
        "id": "eef5bbeb-efdd-48ec-ae0f-eff51e644279",
        "created_at": "2023-08-28T19:16:04.469Z",
        "updated_at": "2023-08-29T07:07:56.894Z",
        "company_id": "main_entity_pk",
        "user_id": "user_entity_pk"
      }
    ],
    "roqUser": [
      {
        "reference": "b59df3cd-cd2e-4e26-9870-dd64b7998e7e",
        "email": "Toney40@yahoo.com",
        "firstName": "Marian",
        "lastName": "Nitzsche",
        "active": true,
        "avatarUrl": "https://cloudflare-ipfs.com/ipfs/Qmd3W5DuhgHirLHGVixi6V76LhCkZUz6pnFt5AJBiyvHye/avatar/972.jpg",
        "tenantId": null
      },
      {
        "reference": "5b3d9344-5e5c-4ca3-a478-bbbe6cb3e36d",
        "email": "Noel10@gmail.com",
        "firstName": "Colten",
        "lastName": "Collins",
        "active": true,
        "avatarUrl": "https://cloudflare-ipfs.com/ipfs/Qmd3W5DuhgHirLHGVixi6V76LhCkZUz6pnFt5AJBiyvHye/avatar/840.jpg",
        "tenantId": null
      },
      {
        "reference": "76109449-245c-4222-aac9-41c73b3d6a72",
        "email": "Daryl46@hotmail.com",
        "firstName": "Beau",
        "lastName": "Stark-Barrows",
        "active": true,
        "avatarUrl": "https://avatars.githubusercontent.com/u/3760635",
        "tenantId": null
      },
      {
        "reference": "b63fdf4a-7148-4198-b69f-c79b3d960652",
        "email": "Adriel.Friesen@hotmail.com",
        "firstName": "Domenica",
        "lastName": "Prosacco",
        "active": true,
        "avatarUrl": "https://avatars.githubusercontent.com/u/79066468",
        "tenantId": null
      },
      {
        "reference": "c85ebe04-0bcd-4c22-86b4-258e9cb3bf2a",
        "email": "Brice.Runolfsdottir57@yahoo.com",
        "firstName": "Mertie",
        "lastName": "Hermiston",
        "active": true,
        "avatarUrl": "https://cloudflare-ipfs.com/ipfs/Qmd3W5DuhgHirLHGVixi6V76LhCkZUz6pnFt5AJBiyvHye/avatar/1172.jpg",
        "tenantId": null
      }
    ]
  },
  {
    "fleet_manager": [
      {
        "id": "c19222ef-0db6-43f7-a74e-c4206edd5559",
        "created_at": "2023-08-28T20:44:03.791Z",
        "updated_at": "2023-08-28T20:02:00.046Z",
        "company_id": "main_entity_pk",
        "user_id": "user_entity_pk"
      },
      {
        "id": "c3e92eec-5bb5-4259-946b-81f0e6f3850f",
        "created_at": "2023-08-28T13:06:30.409Z",
        "updated_at": "2023-08-28T14:40:47.661Z",
        "company_id": "main_entity_pk",
        "user_id": "user_entity_pk"
      },
      {
        "id": "6388e06d-d811-4b4d-b3d4-79b5e9d2213f",
        "created_at": "2023-08-29T10:24:09.239Z",
        "updated_at": "2023-08-29T09:36:24.810Z",
        "company_id": "main_entity_pk",
        "user_id": "user_entity_pk"
      },
      {
        "id": "f74116bc-a5b0-4f10-80c5-aa83be992637",
        "created_at": "2023-08-29T03:54:22.165Z",
        "updated_at": "2023-08-29T08:24:13.613Z",
        "company_id": "main_entity_pk",
        "user_id": "user_entity_pk"
      },
      {
        "id": "58b4c5f5-ecff-468b-acb9-16aa44634584",
        "created_at": "2023-08-28T22:33:05.898Z",
        "updated_at": "2023-08-29T00:21:00.165Z",
        "company_id": "main_entity_pk",
        "user_id": "user_entity_pk"
      }
    ],
    "car": [
      {
        "id": "a5bb3776-87de-4fa4-945a-2953faa4981b",
        "make": "Toyota",
        "model": "Camry",
        "year": 26412,
        "location": "New York",
        "status": "Available",
        "created_at": "2023-08-28T22:47:31.161Z",
        "updated_at": "2023-08-28T19:24:56.334Z",
        "fleet_manager_id": "f74116bc-a5b0-4f10-80c5-aa83be992637"
      },
      {
        "id": "cfe09e6e-4f8c-4136-b432-58c4caf7b13c",
        "make": "Honda",
        "model": "Civic",
        "year": 36292,
        "location": "Los Angeles",
        "status": "Booked",
        "created_at": "2023-08-28T21:45:24.788Z",
        "updated_at": "2023-08-28T21:05:42.157Z",
        "fleet_manager_id": "c3e92eec-5bb5-4259-946b-81f0e6f3850f"
      },
      {
        "id": "a2861c53-694a-47e1-9cab-e769b14d0ac0",
        "make": "Ford",
        "model": "Focus",
        "year": 84962,
        "location": "Chicago",
        "status": "In Repair",
        "created_at": "2023-08-29T05:58:07.938Z",
        "updated_at": "2023-08-29T07:20:47.150Z",
        "fleet_manager_id": "f74116bc-a5b0-4f10-80c5-aa83be992637"
      },
      {
        "id": "ec3b6c9f-fd4c-4785-a061-2135771bd165",
        "make": "Chevrolet",
        "model": "Malibu",
        "year": 12275,
        "location": "Houston",
        "status": "Sold",
        "created_at": "2023-08-29T05:37:18.679Z",
        "updated_at": "2023-08-28T14:15:47.447Z",
        "fleet_manager_id": "f74116bc-a5b0-4f10-80c5-aa83be992637"
      },
      {
        "id": "bb5fb2db-5295-42ae-baf6-6710fcbc297b",
        "make": "BMW",
        "model": "X5",
        "year": 92072,
        "location": "Miami",
        "status": "On Hold",
        "created_at": "2023-08-28T16:12:33.691Z",
        "updated_at": "2023-08-28T22:01:19.767Z",
        "fleet_manager_id": "c19222ef-0db6-43f7-a74e-c4206edd5559"
      }
    ],
    "booking": [
      {
        "id": "c32359a2-6704-4933-b726-ffe32eecd374",
        "start_time": "2023-08-29T00:45:28.645Z",
        "end_time": "2023-08-29T04:29:48.780Z",
        "created_at": "2023-08-28T14:20:55.156Z",
        "updated_at": "2023-08-28T13:03:25.176Z",
        "billing": "Credit Card",
        "car_id": "a5bb3776-87de-4fa4-945a-2953faa4981b",
        "guest_id": "user_entity_pk"
      },
      {
        "id": "57bbe4f3-2e19-4b08-ae4d-63d0bf4836ca",
        "start_time": "2023-08-29T02:01:18.904Z",
        "end_time": "2023-08-29T01:46:14.394Z",
        "created_at": "2023-08-28T11:13:16.960Z",
        "updated_at": "2023-08-28T17:25:27.769Z",
        "billing": "PayPal",
        "car_id": "bb5fb2db-5295-42ae-baf6-6710fcbc297b",
        "guest_id": "user_entity_pk"
      },
      {
        "id": "52777630-bd54-4a6f-8298-e660a49f0911",
        "start_time": "2023-08-29T03:19:00.196Z",
        "end_time": "2023-08-29T00:52:53.940Z",
        "created_at": "2023-08-28T22:39:54.212Z",
        "updated_at": "2023-08-29T10:11:07.009Z",
        "billing": "Bank Transfer",
        "car_id": "ec3b6c9f-fd4c-4785-a061-2135771bd165",
        "guest_id": "user_entity_pk"
      },
      {
        "id": "fc52471f-e31c-441d-a643-d2f32b6737a6",
        "start_time": "2023-08-29T01:18:14.530Z",
        "end_time": "2023-08-28T11:16:16.741Z",
        "created_at": "2023-08-28T21:38:25.217Z",
        "updated_at": "2023-08-28T19:49:45.966Z",
        "billing": "Cash",
        "car_id": "a5bb3776-87de-4fa4-945a-2953faa4981b",
        "guest_id": "user_entity_pk"
      },
      {
        "id": "f8aba4ec-93b3-4e36-a126-029d1b8f9f41",
        "start_time": "2023-08-29T05:28:40.567Z",
        "end_time": "2023-08-28T15:31:33.758Z",
        "created_at": "2023-08-28T19:24:36.238Z",
        "updated_at": "2023-08-28T16:25:57.630Z",
        "billing": "Mobile Payment",
        "car_id": "a5bb3776-87de-4fa4-945a-2953faa4981b",
        "guest_id": "user_entity_pk"
      }
    ],
    "admin": [
      {
        "id": "aa046f0a-6cd5-40c0-a0b5-5895b5c2a843",
        "created_at": "2023-08-28T13:42:40.022Z",
        "updated_at": "2023-08-28T16:43:11.211Z",
        "company_id": "main_entity_pk",
        "user_id": "user_entity_pk"
      },
      {
        "id": "0e1a932e-730e-44ae-b360-174407410613",
        "created_at": "2023-08-29T05:19:21.631Z",
        "updated_at": "2023-08-29T04:32:10.379Z",
        "company_id": "main_entity_pk",
        "user_id": "user_entity_pk"
      },
      {
        "id": "e171e0a7-7e41-448b-abdd-605e89d04c5c",
        "created_at": "2023-08-28T16:01:09.203Z",
        "updated_at": "2023-08-29T10:33:43.172Z",
        "company_id": "main_entity_pk",
        "user_id": "user_entity_pk"
      },
      {
        "id": "6e84848d-0993-4771-9660-092e8c9efbc8",
        "created_at": "2023-08-28T15:45:05.329Z",
        "updated_at": "2023-08-28T15:07:38.737Z",
        "company_id": "main_entity_pk",
        "user_id": "user_entity_pk"
      },
      {
        "id": "36fc2f61-736e-4c80-aa24-c21f3ac3a447",
        "created_at": "2023-08-29T01:26:11.176Z",
        "updated_at": "2023-08-29T06:36:14.102Z",
        "company_id": "main_entity_pk",
        "user_id": "user_entity_pk"
      }
    ],
    "roqUser": [
      {
        "reference": "f22e7c46-65cf-4d4d-9cdf-f757b8672bf6",
        "email": "Vivian.Schumm93@hotmail.com",
        "firstName": "Lester",
        "lastName": "McGlynn",
        "active": true,
        "avatarUrl": "https://cloudflare-ipfs.com/ipfs/Qmd3W5DuhgHirLHGVixi6V76LhCkZUz6pnFt5AJBiyvHye/avatar/171.jpg",
        "tenantId": null
      },
      {
        "reference": "9e93e611-da10-470e-9cc5-d8b261ef18ab",
        "email": "Eryn97@gmail.com",
        "firstName": "Amina",
        "lastName": "Kutch",
        "active": true,
        "avatarUrl": "https://cloudflare-ipfs.com/ipfs/Qmd3W5DuhgHirLHGVixi6V76LhCkZUz6pnFt5AJBiyvHye/avatar/1236.jpg",
        "tenantId": null
      },
      {
        "reference": "74442141-ae5a-4cd2-bbc9-7f6ffbc8dce3",
        "email": "Vergie37@yahoo.com",
        "firstName": "Electa",
        "lastName": "Legros",
        "active": true,
        "avatarUrl": "https://avatars.githubusercontent.com/u/77460915",
        "tenantId": null
      },
      {
        "reference": "d6068be4-22d0-4e3b-8522-2bdaf90d346f",
        "email": "Marilie_Macejkovic@yahoo.com",
        "firstName": "Emmett",
        "lastName": "Boyer",
        "active": true,
        "avatarUrl": "https://avatars.githubusercontent.com/u/48108614",
        "tenantId": null
      },
      {
        "reference": "a4ecc97e-49ef-4eeb-89a1-fb870e53589b",
        "email": "King.Yundt40@hotmail.com",
        "firstName": "Benedict",
        "lastName": "Daniel",
        "active": true,
        "avatarUrl": "https://avatars.githubusercontent.com/u/52490969",
        "tenantId": null
      }
    ]
  },
  {
    "fleet_manager": [
      {
        "id": "cfb7271c-1d5b-483b-8041-8fdf59bc7f43",
        "created_at": "2023-08-29T04:26:02.022Z",
        "updated_at": "2023-08-29T08:30:48.364Z",
        "company_id": "main_entity_pk",
        "user_id": "user_entity_pk"
      },
      {
        "id": "7ab5442f-dedd-4a4f-86f4-92583274b402",
        "created_at": "2023-08-28T17:44:13.221Z",
        "updated_at": "2023-08-29T04:21:19.864Z",
        "company_id": "main_entity_pk",
        "user_id": "user_entity_pk"
      },
      {
        "id": "0d6146a2-7783-40ba-b8b3-13fd36fdb007",
        "created_at": "2023-08-28T12:45:35.106Z",
        "updated_at": "2023-08-28T11:25:23.316Z",
        "company_id": "main_entity_pk",
        "user_id": "user_entity_pk"
      },
      {
        "id": "aa8a9eed-84d3-4b6d-8bc1-d0629fd0ad4c",
        "created_at": "2023-08-29T05:32:19.407Z",
        "updated_at": "2023-08-28T23:51:34.418Z",
        "company_id": "main_entity_pk",
        "user_id": "user_entity_pk"
      },
      {
        "id": "a184d0ed-ffed-4599-a501-fcdc7e7f9c59",
        "created_at": "2023-08-28T19:55:10.696Z",
        "updated_at": "2023-08-29T09:47:38.797Z",
        "company_id": "main_entity_pk",
        "user_id": "user_entity_pk"
      }
    ],
    "car": [
      {
        "id": "47a7c99c-edb8-4527-a08e-fc4a57042115",
        "make": "Toyota",
        "model": "Camry",
        "year": 17363,
        "location": "Los Angeles",
        "status": "Available",
        "created_at": "2023-08-29T00:59:24.791Z",
        "updated_at": "2023-08-28T15:18:17.898Z",
        "fleet_manager_id": "7ab5442f-dedd-4a4f-86f4-92583274b402"
      },
      {
        "id": "c4b3d8ac-06c5-47eb-9ef1-c563c1bc560b",
        "make": "Honda",
        "model": "Civic",
        "year": 28003,
        "location": "New York",
        "status": "Booked",
        "created_at": "2023-08-28T23:14:52.291Z",
        "updated_at": "2023-08-29T02:09:36.135Z",
        "fleet_manager_id": "0d6146a2-7783-40ba-b8b3-13fd36fdb007"
      },
      {
        "id": "0863491c-e325-4ecf-8700-ef98e90cd0d2",
        "make": "Ford",
        "model": "Mustang",
        "year": 72365,
        "location": "Chicago",
        "status": "In Repair",
        "created_at": "2023-08-29T02:42:06.006Z",
        "updated_at": "2023-08-28T23:11:49.556Z",
        "fleet_manager_id": "0d6146a2-7783-40ba-b8b3-13fd36fdb007"
      },
      {
        "id": "b654a32c-c005-4b87-a89a-9c0e7c5c2f6b",
        "make": "Chevrolet",
        "model": "Cruze",
        "year": 84364,
        "location": "San Francisco",
        "status": "Sold",
        "created_at": "2023-08-29T06:16:14.014Z",
        "updated_at": "2023-08-28T15:30:52.311Z",
        "fleet_manager_id": "aa8a9eed-84d3-4b6d-8bc1-d0629fd0ad4c"
      },
      {
        "id": "7f3a69cd-a346-46f5-9cd9-48a3983e0e76",
        "make": "BMW",
        "model": "X5",
        "year": 24423,
        "location": "Miami",
        "status": "Rented",
        "created_at": "2023-08-29T06:44:14.048Z",
        "updated_at": "2023-08-29T05:08:17.672Z",
        "fleet_manager_id": "a184d0ed-ffed-4599-a501-fcdc7e7f9c59"
      }
    ],
    "booking": [
      {
        "id": "4bf172d6-dd6f-468c-ab7e-1c602f489143",
        "start_time": "2023-08-29T04:29:36.771Z",
        "end_time": "2023-08-28T14:57:46.390Z",
        "created_at": "2023-08-29T10:47:26.008Z",
        "updated_at": "2023-08-28T12:33:41.816Z",
        "billing": "Credit Card",
        "car_id": "c4b3d8ac-06c5-47eb-9ef1-c563c1bc560b",
        "guest_id": "user_entity_pk"
      },
      {
        "id": "3c501248-17f5-4c49-8786-18098f1c11c1",
        "start_time": "2023-08-28T23:04:50.820Z",
        "end_time": "2023-08-28T18:29:35.382Z",
        "created_at": "2023-08-28T12:43:31.941Z",
        "updated_at": "2023-08-28T20:27:18.059Z",
        "billing": "PayPal",
        "car_id": "7f3a69cd-a346-46f5-9cd9-48a3983e0e76",
        "guest_id": "user_entity_pk"
      },
      {
        "id": "2f2bc5a9-ce30-4c49-a7a9-64be3f763600",
        "start_time": "2023-08-29T10:29:23.306Z",
        "end_time": "2023-08-29T09:31:34.134Z",
        "created_at": "2023-08-29T07:23:33.566Z",
        "updated_at": "2023-08-29T09:11:56.895Z",
        "billing": "Bank Transfer",
        "car_id": "c4b3d8ac-06c5-47eb-9ef1-c563c1bc560b",
        "guest_id": "user_entity_pk"
      },
      {
        "id": "c43d162d-3faa-4fc9-ad08-ca2c06a3535c",
        "start_time": "2023-08-29T00:49:45.968Z",
        "end_time": "2023-08-28T12:19:15.530Z",
        "created_at": "2023-08-29T06:31:12.877Z",
        "updated_at": "2023-08-28T13:52:33.699Z",
        "billing": "Cash",
        "car_id": "7f3a69cd-a346-46f5-9cd9-48a3983e0e76",
        "guest_id": "user_entity_pk"
      },
      {
        "id": "eec5aba8-2170-4dae-85f4-af4de10be959",
        "start_time": "2023-08-28T18:24:53.555Z",
        "end_time": "2023-08-28T19:28:48.718Z",
        "created_at": "2023-08-29T05:09:33.072Z",
        "updated_at": "2023-08-29T02:36:23.799Z",
        "billing": "Mobile Payment",
        "car_id": "47a7c99c-edb8-4527-a08e-fc4a57042115",
        "guest_id": "user_entity_pk"
      }
    ],
    "admin": [
      {
        "id": "6ad488db-0da2-47df-adba-912e139fb785",
        "created_at": "2023-08-28T17:40:48.119Z",
        "updated_at": "2023-08-29T10:42:07.704Z",
        "company_id": "main_entity_pk",
        "user_id": "user_entity_pk"
      },
      {
        "id": "efe5cecc-99b4-4594-b6a6-0104463a6f4e",
        "created_at": "2023-08-28T17:11:51.129Z",
        "updated_at": "2023-08-28T22:51:22.634Z",
        "company_id": "main_entity_pk",
        "user_id": "user_entity_pk"
      },
      {
        "id": "3e61291e-03a1-4444-9b5c-42bfb9f5dbf7",
        "created_at": "2023-08-28T22:30:29.203Z",
        "updated_at": "2023-08-28T21:58:30.699Z",
        "company_id": "main_entity_pk",
        "user_id": "user_entity_pk"
      },
      {
        "id": "56869d58-3908-4d2d-800c-6d67b73c20bb",
        "created_at": "2023-08-28T12:44:55.235Z",
        "updated_at": "2023-08-29T09:09:22.542Z",
        "company_id": "main_entity_pk",
        "user_id": "user_entity_pk"
      },
      {
        "id": "509afede-f0b9-408f-95ba-4ddfc822b4a2",
        "created_at": "2023-08-29T07:52:51.206Z",
        "updated_at": "2023-08-28T21:34:18.278Z",
        "company_id": "main_entity_pk",
        "user_id": "user_entity_pk"
      }
    ],
    "roqUser": [
      {
        "reference": "ef8a4586-ba6a-4832-a3e7-69b0f19f9d0d",
        "email": "Nicholaus39@yahoo.com",
        "firstName": "Candice",
        "lastName": "Bahringer",
        "active": true,
        "avatarUrl": "https://avatars.githubusercontent.com/u/16849115",
        "tenantId": null
      },
      {
        "reference": "afd9543b-25c0-425c-ba7e-907be2815ed5",
        "email": "Sonny.Haley20@hotmail.com",
        "firstName": "Ferne",
        "lastName": "Stokes",
        "active": true,
        "avatarUrl": "https://avatars.githubusercontent.com/u/69608959",
        "tenantId": null
      },
      {
        "reference": "6b345e93-a42f-4406-b08b-c5318f2f79dd",
        "email": "Laron_Buckridge@hotmail.com",
        "firstName": "Erin",
        "lastName": "Lemke",
        "active": true,
        "avatarUrl": "https://avatars.githubusercontent.com/u/68391948",
        "tenantId": null
      },
      {
        "reference": "ad934cd0-c752-4da5-aae4-34d4327ae346",
        "email": "Janice61@hotmail.com",
        "firstName": "Kenna",
        "lastName": "Purdy",
        "active": true,
        "avatarUrl": "https://avatars.githubusercontent.com/u/40634722",
        "tenantId": null
      },
      {
        "reference": "05c55884-f509-4783-9a4e-f6a7049b5510",
        "email": "Garnett.Hermiston16@hotmail.com",
        "firstName": "Yasmeen",
        "lastName": "Renner",
        "active": true,
        "avatarUrl": "https://cloudflare-ipfs.com/ipfs/Qmd3W5DuhgHirLHGVixi6V76LhCkZUz6pnFt5AJBiyvHye/avatar/255.jpg",
        "tenantId": null
      }
    ]
  },
  {
    "fleet_manager": [
      {
        "id": "9f3d16ab-06b9-4725-81ae-6bbf4d986fc1",
        "created_at": "2023-08-28T11:02:52.729Z",
        "updated_at": "2023-08-28T14:00:27.497Z",
        "company_id": "main_entity_pk",
        "user_id": "user_entity_pk"
      },
      {
        "id": "470efe53-20b6-42f2-a57f-ebde5f896d29",
        "created_at": "2023-08-28T22:18:10.569Z",
        "updated_at": "2023-08-28T18:50:01.786Z",
        "company_id": "main_entity_pk",
        "user_id": "user_entity_pk"
      },
      {
        "id": "e93608de-652a-4a7e-946a-3ed334d05251",
        "created_at": "2023-08-28T16:35:18.860Z",
        "updated_at": "2023-08-28T19:00:04.095Z",
        "company_id": "main_entity_pk",
        "user_id": "user_entity_pk"
      },
      {
        "id": "e6412b0a-f0ca-411f-9a9d-7b7cb016dc5b",
        "created_at": "2023-08-29T02:01:11.818Z",
        "updated_at": "2023-08-28T12:12:17.722Z",
        "company_id": "main_entity_pk",
        "user_id": "user_entity_pk"
      },
      {
        "id": "95b329ba-e17a-40fc-8bf6-1b47ac46d16a",
        "created_at": "2023-08-28T23:15:47.198Z",
        "updated_at": "2023-08-29T05:05:39.997Z",
        "company_id": "main_entity_pk",
        "user_id": "user_entity_pk"
      }
    ],
    "car": [
      {
        "id": "b113b7de-f240-4661-9bc7-3d4c302d5d00",
        "make": "Toyota",
        "model": "Camry",
        "year": 36266,
        "location": "New York",
        "status": "Available",
        "created_at": "2023-08-28T14:39:00.064Z",
        "updated_at": "2023-08-29T10:48:56.198Z",
        "fleet_manager_id": "9f3d16ab-06b9-4725-81ae-6bbf4d986fc1"
      },
      {
        "id": "9ab50e7c-2963-402a-9524-244f3216f15d",
        "make": "Honda",
        "model": "Civic",
        "year": 36113,
        "location": "Los Angeles",
        "status": "Booked",
        "created_at": "2023-08-28T17:22:54.350Z",
        "updated_at": "2023-08-28T14:47:24.862Z",
        "fleet_manager_id": "e93608de-652a-4a7e-946a-3ed334d05251"
      },
      {
        "id": "5829cf67-bea5-495b-aaa1-83720626a18b",
        "make": "Ford",
        "model": "Mustang",
        "year": 86349,
        "location": "Chicago",
        "status": "Under Maintenance",
        "created_at": "2023-08-29T06:20:44.278Z",
        "updated_at": "2023-08-28T13:08:46.219Z",
        "fleet_manager_id": "9f3d16ab-06b9-4725-81ae-6bbf4d986fc1"
      },
      {
        "id": "ea841bab-2f5b-4f80-b475-1b4f560bc82e",
        "make": "Chevrolet",
        "model": "Cruze",
        "year": 64138,
        "location": "Houston",
        "status": "Out of Service",
        "created_at": "2023-08-28T20:27:53.210Z",
        "updated_at": "2023-08-28T13:03:26.973Z",
        "fleet_manager_id": "e93608de-652a-4a7e-946a-3ed334d05251"
      },
      {
        "id": "f177d749-b013-4e57-bb19-f329c1e075a0",
        "make": "BMW",
        "model": "X5",
        "year": 64320,
        "location": "Miami",
        "status": "Rented",
        "created_at": "2023-08-28T15:38:02.186Z",
        "updated_at": "2023-08-29T09:54:17.307Z",
        "fleet_manager_id": "9f3d16ab-06b9-4725-81ae-6bbf4d986fc1"
      }
    ],
    "booking": [
      {
        "id": "acf71817-a9e7-440d-b2ac-c82c19103b16",
        "start_time": "2023-08-28T19:33:01.611Z",
        "end_time": "2023-08-28T22:03:32.756Z",
        "created_at": "2023-08-28T21:35:22.622Z",
        "updated_at": "2023-08-28T19:24:36.493Z",
        "billing": "Credit Card",
        "car_id": "9ab50e7c-2963-402a-9524-244f3216f15d",
        "guest_id": "user_entity_pk"
      },
      {
        "id": "1d0556ce-6862-4686-a485-b4323abbdad1",
        "start_time": "2023-08-29T01:29:50.474Z",
        "end_time": "2023-08-28T17:07:48.818Z",
        "created_at": "2023-08-28T22:44:20.596Z",
        "updated_at": "2023-08-28T17:39:48.196Z",
        "billing": "PayPal",
        "car_id": "9ab50e7c-2963-402a-9524-244f3216f15d",
        "guest_id": "user_entity_pk"
      },
      {
        "id": "a7770c0f-b755-4142-abcd-b9be36667d5f",
        "start_time": "2023-08-28T17:38:31.039Z",
        "end_time": "2023-08-29T09:55:02.941Z",
        "created_at": "2023-08-29T07:46:51.305Z",
        "updated_at": "2023-08-28T20:27:21.122Z",
        "billing": "Bank Transfer",
        "car_id": "5829cf67-bea5-495b-aaa1-83720626a18b",
        "guest_id": "user_entity_pk"
      },
      {
        "id": "898c8567-25e7-414e-823d-916c64630df7",
        "start_time": "2023-08-29T08:10:28.940Z",
        "end_time": "2023-08-29T10:26:19.453Z",
        "created_at": "2023-08-28T22:58:08.840Z",
        "updated_at": "2023-08-29T05:43:23.221Z",
        "billing": "Cash",
        "car_id": "b113b7de-f240-4661-9bc7-3d4c302d5d00",
        "guest_id": "user_entity_pk"
      },
      {
        "id": "f8022e53-4bc1-4523-9fcd-a7abef5c9549",
        "start_time": "2023-08-29T00:26:45.371Z",
        "end_time": "2023-08-29T07:33:55.536Z",
        "created_at": "2023-08-29T09:06:09.198Z",
        "updated_at": "2023-08-28T14:35:07.252Z",
        "billing": "Debit Card",
        "car_id": "b113b7de-f240-4661-9bc7-3d4c302d5d00",
        "guest_id": "user_entity_pk"
      }
    ],
    "admin": [
      {
        "id": "3dd873b3-17e5-4b08-bdba-4ee69862183a",
        "created_at": "2023-08-28T22:11:50.361Z",
        "updated_at": "2023-08-29T06:45:35.012Z",
        "company_id": "main_entity_pk",
        "user_id": "user_entity_pk"
      },
      {
        "id": "41c5113b-a49e-4488-b260-b15b4d6d4f2e",
        "created_at": "2023-08-29T05:04:43.313Z",
        "updated_at": "2023-08-28T23:50:24.745Z",
        "company_id": "main_entity_pk",
        "user_id": "user_entity_pk"
      },
      {
        "id": "a1bbc7e6-2645-4636-ba1f-4e34ebda2a7a",
        "created_at": "2023-08-28T16:15:17.511Z",
        "updated_at": "2023-08-29T10:42:19.444Z",
        "company_id": "main_entity_pk",
        "user_id": "user_entity_pk"
      },
      {
        "id": "f054246a-4fe1-45cb-8a44-2fdca5b4d932",
        "created_at": "2023-08-28T11:52:47.369Z",
        "updated_at": "2023-08-29T09:31:56.046Z",
        "company_id": "main_entity_pk",
        "user_id": "user_entity_pk"
      },
      {
        "id": "b2f00cb3-1c9d-41b2-afd9-6e5ebff129c3",
        "created_at": "2023-08-28T23:23:26.156Z",
        "updated_at": "2023-08-29T03:39:34.173Z",
        "company_id": "main_entity_pk",
        "user_id": "user_entity_pk"
      }
    ],
    "roqUser": [
      {
        "reference": "bbc4eb9e-8485-4872-9631-92c8fb70e6c8",
        "email": "Wilhelmine84@gmail.com",
        "firstName": "Colleen",
        "lastName": "Weber",
        "active": true,
        "avatarUrl": "https://avatars.githubusercontent.com/u/29355252",
        "tenantId": null
      },
      {
        "reference": "19c6dabb-1fec-44d1-b816-1e4e91bf9de9",
        "email": "Melba40@hotmail.com",
        "firstName": "Amani",
        "lastName": "Jacobi",
        "active": true,
        "avatarUrl": "https://avatars.githubusercontent.com/u/54304108",
        "tenantId": null
      },
      {
        "reference": "3e080e61-ad8a-43f8-b76c-05c0996e41a1",
        "email": "Ashleigh_Bashirian@hotmail.com",
        "firstName": "Alek",
        "lastName": "Weissnat",
        "active": true,
        "avatarUrl": "https://avatars.githubusercontent.com/u/68755334",
        "tenantId": null
      },
      {
        "reference": "c4598798-101c-472f-9c9c-cd9d7d36a4c2",
        "email": "Sibyl95@yahoo.com",
        "firstName": "Ashlee",
        "lastName": "Raynor",
        "active": true,
        "avatarUrl": "https://avatars.githubusercontent.com/u/94460589",
        "tenantId": null
      },
      {
        "reference": "0dfe9033-bc73-487b-8f48-ba9a19b0b539",
        "email": "Stella_Cummerata67@gmail.com",
        "firstName": "Alexandrea",
        "lastName": "Mohr",
        "active": true,
        "avatarUrl": "https://avatars.githubusercontent.com/u/1014863",
        "tenantId": null
      }
    ]
  },
  {
    "fleet_manager": [
      {
        "id": "455b1fee-6fcf-45c1-af57-01b6345d7dea",
        "created_at": "2023-08-29T00:55:30.450Z",
        "updated_at": "2023-08-29T04:44:50.526Z",
        "company_id": "main_entity_pk",
        "user_id": "user_entity_pk"
      },
      {
        "id": "c6535468-51b0-424f-ac6f-445545109963",
        "created_at": "2023-08-28T13:13:15.971Z",
        "updated_at": "2023-08-28T21:54:34.978Z",
        "company_id": "main_entity_pk",
        "user_id": "user_entity_pk"
      },
      {
        "id": "dd559f5d-7035-44e8-93ab-3dd0509a4386",
        "created_at": "2023-08-28T12:22:17.401Z",
        "updated_at": "2023-08-28T19:12:54.735Z",
        "company_id": "main_entity_pk",
        "user_id": "user_entity_pk"
      },
      {
        "id": "295d7eed-3a0d-4281-8583-1de844ed9a04",
        "created_at": "2023-08-29T09:22:25.020Z",
        "updated_at": "2023-08-28T17:47:41.572Z",
        "company_id": "main_entity_pk",
        "user_id": "user_entity_pk"
      },
      {
        "id": "e5f4743f-bb6d-4e31-8383-e799532d2299",
        "created_at": "2023-08-28T23:03:27.053Z",
        "updated_at": "2023-08-29T04:45:27.520Z",
        "company_id": "main_entity_pk",
        "user_id": "user_entity_pk"
      }
    ],
    "car": [
      {
        "id": "7665b92a-4cf8-4769-827c-b102a2c8728e",
        "make": "Toyota",
        "model": "Camry",
        "year": 92590,
        "location": "New York",
        "status": "Available",
        "created_at": "2023-08-29T09:44:24.653Z",
        "updated_at": "2023-08-28T20:38:43.997Z",
        "fleet_manager_id": "455b1fee-6fcf-45c1-af57-01b6345d7dea"
      },
      {
        "id": "ad4156a1-cf14-4da4-b99a-cacf1bc787ca",
        "make": "Honda",
        "model": "Civic",
        "year": 11340,
        "location": "Los Angeles",
        "status": "Booked",
        "created_at": "2023-08-28T16:39:03.227Z",
        "updated_at": "2023-08-28T20:01:37.256Z",
        "fleet_manager_id": "455b1fee-6fcf-45c1-af57-01b6345d7dea"
      },
      {
        "id": "c5cf6494-d34d-41e9-9843-daba783a4e61",
        "make": "Ford",
        "model": "Mustang",
        "year": 27630,
        "location": "Chicago",
        "status": "In Service",
        "created_at": "2023-08-29T04:22:52.768Z",
        "updated_at": "2023-08-29T10:02:03.902Z",
        "fleet_manager_id": "455b1fee-6fcf-45c1-af57-01b6345d7dea"
      },
      {
        "id": "f28535bd-62f4-4534-b893-29f353c317bd",
        "make": "Chevrolet",
        "model": "Cruze",
        "year": 96584,
        "location": "Houston",
        "status": "Under Maintenance",
        "created_at": "2023-08-28T12:47:13.591Z",
        "updated_at": "2023-08-28T21:36:20.361Z",
        "fleet_manager_id": "c6535468-51b0-424f-ac6f-445545109963"
      },
      {
        "id": "1def760f-8f5c-4362-a832-0cbe3a0a3dbe",
        "make": "BMW",
        "model": "X5",
        "year": 9512,
        "location": "Miami",
        "status": "Sold",
        "created_at": "2023-08-28T12:59:01.374Z",
        "updated_at": "2023-08-28T17:59:38.533Z",
        "fleet_manager_id": "c6535468-51b0-424f-ac6f-445545109963"
      }
    ],
    "booking": [
      {
        "id": "9c3e3fcd-aec8-461e-b13c-9d26c5f329c2",
        "start_time": "2023-08-29T10:46:46.523Z",
        "end_time": "2023-08-29T01:51:25.993Z",
        "created_at": "2023-08-28T18:06:08.468Z",
        "updated_at": "2023-08-29T08:07:36.424Z",
        "billing": "Credit Card",
        "car_id": "7665b92a-4cf8-4769-827c-b102a2c8728e",
        "guest_id": "user_entity_pk"
      },
      {
        "id": "7c78d081-3b99-4be7-b7b6-d1c75edc3a6b",
        "start_time": "2023-08-28T13:06:53.842Z",
        "end_time": "2023-08-28T21:58:42.067Z",
        "created_at": "2023-08-29T08:22:46.117Z",
        "updated_at": "2023-08-29T00:18:18.580Z",
        "billing": "PayPal",
        "car_id": "ad4156a1-cf14-4da4-b99a-cacf1bc787ca",
        "guest_id": "user_entity_pk"
      },
      {
        "id": "cb0cce4d-5579-456e-98bb-a4541af2393e",
        "start_time": "2023-08-28T21:56:14.817Z",
        "end_time": "2023-08-29T09:22:57.355Z",
        "created_at": "2023-08-29T00:02:04.172Z",
        "updated_at": "2023-08-29T02:03:19.528Z",
        "billing": "Bank Transfer",
        "car_id": "7665b92a-4cf8-4769-827c-b102a2c8728e",
        "guest_id": "user_entity_pk"
      },
      {
        "id": "15402a87-89c3-4ccf-890d-ac2595769f9e",
        "start_time": "2023-08-28T16:55:28.677Z",
        "end_time": "2023-08-28T18:17:17.567Z",
        "created_at": "2023-08-28T11:12:04.903Z",
        "updated_at": "2023-08-28T11:26:47.580Z",
        "billing": "Cash",
        "car_id": "ad4156a1-cf14-4da4-b99a-cacf1bc787ca",
        "guest_id": "user_entity_pk"
      },
      {
        "id": "36c74b5f-aab1-4eda-b896-cb315830da7b",
        "start_time": "2023-08-28T19:16:28.806Z",
        "end_time": "2023-08-28T19:53:50.880Z",
        "created_at": "2023-08-29T01:43:00.581Z",
        "updated_at": "2023-08-28T11:11:47.986Z",
        "billing": "Apple Pay",
        "car_id": "f28535bd-62f4-4534-b893-29f353c317bd",
        "guest_id": "user_entity_pk"
      }
    ],
    "admin": [
      {
        "id": "0d671b2e-c5bc-4bf1-86a7-a7a97239230d",
        "created_at": "2023-08-29T04:40:39.410Z",
        "updated_at": "2023-08-29T09:16:14.649Z",
        "company_id": "main_entity_pk",
        "user_id": "user_entity_pk"
      },
      {
        "id": "2ffe59b6-9d36-4a6a-ab7e-8ed5b7eda644",
        "created_at": "2023-08-29T07:32:25.589Z",
        "updated_at": "2023-08-28T19:01:04.221Z",
        "company_id": "main_entity_pk",
        "user_id": "user_entity_pk"
      },
      {
        "id": "684ac129-9305-4628-a52d-940c4f10f46f",
        "created_at": "2023-08-29T06:38:08.707Z",
        "updated_at": "2023-08-28T11:31:11.322Z",
        "company_id": "main_entity_pk",
        "user_id": "user_entity_pk"
      },
      {
        "id": "ab231147-a828-49fe-b5f6-87a6a668dcba",
        "created_at": "2023-08-28T22:21:46.647Z",
        "updated_at": "2023-08-29T01:19:45.045Z",
        "company_id": "main_entity_pk",
        "user_id": "user_entity_pk"
      },
      {
        "id": "9a3d5cd5-4b1b-4005-bb8c-90fc519bf966",
        "created_at": "2023-08-29T09:30:54.951Z",
        "updated_at": "2023-08-28T16:54:44.903Z",
        "company_id": "main_entity_pk",
        "user_id": "user_entity_pk"
      }
    ],
    "roqUser": [
      {
        "reference": "06d91da8-a1bf-43d8-8cc2-7276e445ca68",
        "email": "Joany8@gmail.com",
        "firstName": "Shanny",
        "lastName": "Kreiger",
        "active": true,
        "avatarUrl": "https://cloudflare-ipfs.com/ipfs/Qmd3W5DuhgHirLHGVixi6V76LhCkZUz6pnFt5AJBiyvHye/avatar/877.jpg",
        "tenantId": null
      },
      {
        "reference": "634a3e76-5166-4762-8824-9b30bb3efa76",
        "email": "Desiree91@gmail.com",
        "firstName": "Melissa",
        "lastName": "Roob",
        "active": true,
        "avatarUrl": "https://cloudflare-ipfs.com/ipfs/Qmd3W5DuhgHirLHGVixi6V76LhCkZUz6pnFt5AJBiyvHye/avatar/466.jpg",
        "tenantId": null
      },
      {
        "reference": "1fa4328d-d18c-482b-bc8b-a330a8063da7",
        "email": "Andreanne79@hotmail.com",
        "firstName": "Cristal",
        "lastName": "Abernathy",
        "active": true,
        "avatarUrl": "https://cloudflare-ipfs.com/ipfs/Qmd3W5DuhgHirLHGVixi6V76LhCkZUz6pnFt5AJBiyvHye/avatar/16.jpg",
        "tenantId": null
      },
      {
        "reference": "77236c94-f5fb-4fff-988e-d7212eb78158",
        "email": "Virginie.Sipes@gmail.com",
        "firstName": "Garrison",
        "lastName": "Durgan",
        "active": true,
        "avatarUrl": "https://avatars.githubusercontent.com/u/40166668",
        "tenantId": null
      },
      {
        "reference": "23fb2de3-b2da-406a-8d38-0efb76c036aa",
        "email": "Orland.Ullrich60@yahoo.com",
        "firstName": "Lesly",
        "lastName": "Daugherty-Stroman",
        "active": true,
        "avatarUrl": "https://cloudflare-ipfs.com/ipfs/Qmd3W5DuhgHirLHGVixi6V76LhCkZUz6pnFt5AJBiyvHye/avatar/724.jpg",
        "tenantId": null
      }
    ]
  }
]
